pipeline_factory/__init__.py
pipeline_factory/_version.py
pipeline_factory/config.py
pipeline_factory/utils.py
pipeline_factory/db/__init__.py
pipeline_factory/db/db.py
pipeline_factory/db/sqlite.py
pipeline_factory/db/sqlite_config.py
pipeline_factory/pipeline/__init__.py
pipeline_factory/pipeline/controlers.py
pipeline_factory/pipeline/models.py
pipeline_factory/pipeline/pipeline.py
pipeline_factory/pipeline/tasks.py
pipeline_factory/server/__init__.py
pipeline_factory/server/main.py
pipeline_factory/server/tasks.py
pipeline_factory/server/worker.py
pipeline_factory/server/templates/list_files.html
pipeline_factory-0.0.1a0.dist-info/METADATA
pipeline_factory-0.0.1a0.dist-info/WHEEL
pipeline_factory-0.0.1a0.dist-info/entry_points.txt
pipeline_factory-0.0.1a0.dist-info/top_level.txt
pipeline_factory-0.0.1a0.dist-info/RECORD
