Metadata-Version: 2.1
Name: pipeline_factory
Version: 0.0.1a0
Summary: Python server framework to define, manage, schedule and execute custom defined code pipelines and series of pipeline across multiple worker processes
Author-email: Hristo Gueorguiev <hristo.gueorguiev@gmail.com>
License: MIT License
Project-URL: Repository, https://github.com/izo0x90/pipeline-factory
Project-URL: Issues, https://github.com/izo0x90/pipeline-factory/issues
Keywords: task,pipeline,schedule,workers,async,pipeline framework
Classifier: Framework :: FastAPI
Classifier: Programming Language :: Python :: 3
Requires-Python: >=3.10
Requires-Dist: fastapi
Requires-Dist: sqlmodel
Requires-Dist: croniter
Provides-Extra: dev
Requires-Dist: pyright ; extra == 'dev'
Requires-Dist: ruff ; extra == 'dev'
Requires-Dist: build ; extra == 'dev'
Requires-Dist: twine ; extra == 'dev'
